cmds/__init__.py
cmds/build/__init__.py
cmds/bundle.py
cmds/config.py
cmds/create.py
cmds/init.py
cmds/picker/__init__.py
cmds/picker/property.py
cmds/strong_build.py
cmds/util.py
macli-1.0.0.dist-info/METADATA
macli-1.0.0.dist-info/WHEEL
macli-1.0.0.dist-info/entry_points.txt
macli-1.0.0.dist-info/RECORD
